Workbook

Sheet Basket
A1: pair_id | B1: category | C1: product_name | D1: retailer | E1: price_usd | F1: net_contents_value | G1: net_contents_unit | H1: uses_per_package | I1: packaging_format | J1: refill_or_concentrate_flag | K1: url | L1: notes
A2: 1 | B2: laundry_detergent | C2: Seventh Generation Free & Clear Liquid Laundry Detergent 90 fl oz | D2: Target | E2: 12.99 | F2: 90 | G2: fl_oz | H2: 60 loads | I2: HDPE jug with cap | J2: 0 | K2: https://www.target.com/p/seventh-generation-liquid-laundry-detergent-free-38-clear-90-fl-oz/-/A-84215092 | L2: Accessed 2026-07-17. Full-package one-time price; conventional same-brand Free & Clear format.
A3: 1 | B3: laundry_detergent | C3: Seventh Generation EasyDose Free & Clear Ultra-Concentrated Laundry Detergent 23.1 fl oz | D3: Target | E3: 13.99 | F3: 23.1 | G3: fl_oz | H3: 66 loads | I3: compact plastic auto-dose bottle | J3: 1 | K3: https://www.target.com/p/seventh-generation-free-38-clear-ultra-concentrated-66-loads-laundry-detergent-8211-23-1-fl-oz/-/A-76158733 | L3: Accessed 2026-07-17. Full-package one-time price; same-brand Free & Clear concentrate and a clean matched comparison.
A4: 2 | B4: coffee | C4: Starbucks Pike Place Roast Medium Roast K-Cup Pods 22ct | D4: Target | E4: 20.99 | F4: 22 | G4: pods | H4: 22 cups | I4: plastic pods plus foil and paperboard carton | J4: 0 | K4: https://www.target.com/p/starbucks-keurig-pike-place-roast-medium-roast-coffee-pods-22-k-cups/-/A-79578014 | L4: Accessed 2026-07-17. Full-package one-time price; promotion excluded.
A5: 2 | B5: coffee | C5: Starbucks Pike Place Roast Medium Ground Coffee 12 oz | D5: Target | E5: 12.79 | F5: 12 | G5: oz | H5: ~34 6-fl-oz cups | I5: laminated flexible coffee bag | J5: 1 | K5: https://www.target.com/p/starbucks-medium-roast-ground-coffee-8212-pike-place-roast-8212-100-arabica-8212-1-bag-12-oz/-/A-12954151 | L5: Accessed 2026-07-17. Full-package one-time price; estimated cup count assumes 10 g ground coffee per 6-fl-oz cup. Same roast as pod row.
A6: 3 | B6: surface_cleaner | C6: Windex Original Blue Window and Glass Cleaner Spray 26 fl oz | D6: Target | E6: 3.99 | F6: 26 | G6: fl_oz | H6: 1 spray bottle | I6: PET trigger bottle | J6: 0 | K6: https://www.target.com/p/windex-original-blue-glass-cleaner-spray-26-fl-oz/-/A-53411349 | L6: Accessed 2026-07-17. Full-package one-time price.
A7: 3 | B7: surface_cleaner | C7: Windex Original Blue Window and Glass Cleaner Refill 67.6 fl oz | D7: Target | E7: 6.99 | F7: 67.6 | G7: fl_oz | H7: 2.6 spray-bottle fills | I7: large plastic refill bottle with cap | J7: 1 | K7: https://www.target.com/p/windex-glass-cleaner-original-blue-refill-bottle-2l-67-6oz/-/A-12972711 | L7: Accessed 2026-07-17. Full-package one-time price; same formula family and 67.6/26 = 2.60 nominal fills.
A8: 4 | B8: beverage | C8: Coca-Cola Original Taste 12 fl oz cans 12-pack | D8: Target | E8: 8.89 | F8: 12 | G8: fl_oz | H8: 12 servings | I8: aluminum cans with paperboard carton | J8: 0 | K8: https://www.target.com/p/coca-cola-12pk-12-fl-oz-cans/-/A-12953464 | L8: Accessed 2026-07-17. Full 12-pack price; net contents are per container.
A9: 4 | B9: beverage | C9: Coca-Cola Original Taste 20 fl oz single bottle | D9: Target | E9: 2.69 | F9: 20 | G9: fl_oz | H9: 1 serving | I9: PET bottle with plastic cap and label | J9: 0 | K9: https://www.target.com/p/coca-cola-20-fl-oz-bottle/-/A-12953529 | L9: Accessed 2026-07-17. Full single-bottle price.
A10: 4 | B10: beverage | C10: Coca-Cola de Mexico 355 mL glass bottles 4-pack | D10: Walmart | E10: 7.22 | F10: 12 | G10: fl_oz | H10: 4 servings | I10: glass bottles with metal caps and carton | J10: 0 | K10: https://www.walmart.com/ip/Coca-Cola-Cane-Sugar-Mexican-Soda-Pop-355-ml-4-Pack-Glass-Bottle/220829933 | L10: Accessed 2026-07-17. Full 4-pack one-time price; each bottle is 355 mL (about 12.0 fl oz). Cane-sugar formulation differs from U.S. Coke, so use for packaging arithmetic only, not a clean price-demand comparison.
A11: 5 | B11: razor | C11: Gillette Sensor3 Comfort Disposable Manual Razors 12ct | D11: Walmart | E11: 14.97 | F11: 12 | G11: razors | H11: up to 144 shaves | I11: plastic handle plus integrated cartridge and blister/cardboard pack | J11: 0 | K11: https://www.walmart.com/ip/Gillette-Sensor3-Comfort-Men-s-Disposable-Razors-12-Razors/2912310135 | L11: Accessed 2026-07-17. Full-package one-time price; manufacturer states up to 12 shaves per razor.
A12: 5 | B12: razor | C12: Gillette Mach3 Handle with 10 Blade Refills | D12: Walmart | E12: 29.97 | F12: 10 | G12: cartridges | H12: up to 150 shaves | I12: durable handle plus replaceable cartridges and carton | J12: 1 | K12: https://www.walmart.com/ip/Gillette-Mach3-Shaving-Razor-for-Men-1-Gillette-3-Blade-Razor-Handle-for-Men-s-Grooming-10-Razor-Blade-Refills-Razor-Blades-with-Lubrication-Strip/7483106556 | L12: Accessed 2026-07-17. Full-package one-time price; manufacturer states up to 15 shaves per cartridge. Normalize by claimed shave before comparison.
A13: 6 | B13: hand_soap | C13: Softsoap Crisp Clean Antibacterial Liquid Hand Soap Pump 11.25 fl oz | D13: Walmart | E13: 2.97 | F13: 11.25 | G13: fl_oz | H13: 1 pump bottle | I13: PET pump bottle | J13: 0 | K13: https://www.walmart.com/ip/Softsoap-Antibacterial-Liquid-Hand-Soap-Crisp-Clean-11-25-Fluid-Ounce-Bottle/180160368 | L13: Accessed 2026-07-17. Full-package one-time price.
... A43: 20 | B43: surface_cleaner | C43: BLUELAND Multi-Surface Cleaner 10 Refill Tablets Fresh Lemon | D43: Amazon | E43: 24 | F43: 24 | G43: fl_oz_per_tablet | H43: 10 x 24-fl-oz fills | I43: dry tablets in retail refill pouch | J43: 1 | K43: https://www.amazon.com/BLUELAND-Multi-surface-Friendly-Products-Cleaning/dp/B09P1Y9RXV | L43: Accessed 2026-07-17. Price shown on Amazon listing/search result; each tablet makes 24 fl oz. Refill tablets do not include the reusable bottle, so use for recurring-use comparison and add/amortize a bottle for first-purchase analysis. Different brand and formula from Windex.

Sheet Read Me
A1: Product-Basket Dataset — Audit & QC
A2: 42 retailer observations | 20 matched groups | prices accessed 2026-07-17
A4: QC metric | B4: Workbook result | D4: Method | E4: Rule | F4: Reason
A5: Rows | B5: =COUNTA(Basket!A2:A43) -> 42 | D5: Price | E5: One-time current price; tax, shipping and subscriptions excluded | F5: Comparable checkout basis
A6: Matched groups | B6: =MAX(Basket!A2:A43) -> 20 | D6: Multipacks | E6: price_usd is the entire package; uses_per_package stores count | F6: Avoid mixing per-unit and package prices
A7: Missing prices | B7: =COUNTBLANK(Basket!E2:E43) -> 0 | D7: Net contents | E7: Per-container contents for beverage multipacks | F7: Supports separate container-mass arithmetic
A8: Missing URLs | B8: =COUNTBLANK(Basket!K2:K43) -> 0 | D8: Matching | E8: Prefer same brand, formula and scent | F8: Reduces quality and formulation confounds
A9: Refill/concentrate/reuse flags | B9: =SUM(Basket!J2:J43) -> 17 | D9: Flags | E9: 1 includes refills, concentrates and durable/reusable alternatives | F9: Follows the seed template's broader convention
A10: Retailers represented | B10: =COUNTA(_xlfn.UNIQUE(Basket!D2:D43)) -> 3 | D10: Sources | E10: Raw product-page URLs remain in Basket column K | F10: Line-by-line audit trail
A11: Package-price convention | B11: price_usd is the full listing/package price; normalize separately
A13: Highest-priority caveats before analysis
A14: Pair | B14: Issue | C14: Implication | D14: Pair | E14: Issue | F14: Implication
A15: 4 | B15: Mexican glass Coke uses cane sugar | C15: Packaging comparison only | D15: 8 | E15: Dishcloth is a functional substitute | F15: Assume lifespan/scenario
A16: 5 | B16: Shave counts are manufacturer maxima | C16: Use sensitivity ranges | D16: 9 | E16: Pitcher is a capital good | F16: Amortize pitcher and filters
A17: 12 | B17: Aveeno refill was marked down | C17: Run prior-price sensitivity | D17: 14 | E17: Concentrate yield is label-dependent | F17: Verify dilution before normalization
A18: 16 | B18: Starter title says 5.29 oz; refill is 1.4 oz | C18: Verify physical net label | D18: 19 | E18: Pack counts differ by material | F18: Compare per fl oz/container
A19: 18 | B19: Only can and PET formats found | C19: Do not imply a glass observation | D19: 20 | E19: Tablet refill excludes bottle and changes brand | F19: Amortize bottle; treat as illustrative
A20: All | B20: Retail prices are a cross-sectional snapshot | C20: Do not infer demand elasticity | D20: All | E20: Local inventory may change | F20: Archive screenshots if used in final paper
A21: All | B21: Packaging masses are intentionally absent | C21: Join the user's reference mass table | D21: All | E21: Promotions mostly excluded | F21: Flag any unavoidable markdowns
A23: Pair | B23: Matched group | C23: Rows | D23: Flagged alternatives
A24: 1 | B24: Laundry detergent: standard vs ultra-concentrate | C24: =COUNTIF(Basket!$A$2:$A$43,A24) -> 2 | D24: =SUMIF(Basket!$A$2:$A$43,A24,Basket!$J$2:$J$43) -> 1
A25: 2 | B25: Coffee: K-Cup pods vs ground bag | C25: =COUNTIF(Basket!$A$2:$A$43,A25) -> 2 | D25: =SUMIF(Basket!$A$2:$A$43,A25,Basket!$J$2:$J$43) -> 1
A26: 3 | B26: Windex spray vs refill | C26: =COUNTIF(Basket!$A$2:$A$43,A26) -> 2 | D26: =SUMIF(Basket!$A$2:$A$43,A26,Basket!$J$2:$J$43) -> 1
A27: 4 | B27: Coca-Cola: can vs PET vs glass | C27: =COUNTIF(Basket!$A$2:$A$43,A27) -> 3 | D27: =SUMIF(Basket!$A$2:$A$43,A27,Basket!$J$2:$J$43) -> 0
A28: 5 | B28: Disposable razor vs cartridge system | C28: =COUNTIF(Basket!$A$2:$A$43,A28) -> 2 | D28: =SUMIF(Basket!$A$2:$A$43,A28,Basket!$J$2:$J$43) -> 1
A29: 6 | B29: Softsoap pump vs refill | C29: =COUNTIF(Basket!$A$2:$A$43,A29) -> 2 | D29: =SUMIF(Basket!$A$2:$A$43,A29,Basket!$J$2:$J$43) -> 1
A30: 7 | B30: Dawn bottle vs refill jug | C30: =COUNTIF(Basket!$A$2:$A$43,A30) -> 2 | D30: =SUMIF(Basket!$A$2:$A$43,A30,Basket!$J$2:$J$43) -> 1
A31: 8 | B31: Paper towels vs reusable dishcloths | C31: =COUNTIF(Basket!$A$2:$A$43,A31) -> 2 | D31: =SUMIF(Basket!$A$2:$A$43,A31,Basket!$J$2:$J$43) -> 1
A32: 9 | B32: Bottled water vs filter pitcher | C32: =COUNTIF(Basket!$A$2:$A$43,A32) -> 2 | D32: =SUMIF(Basket!$A$2:$A$43,A32,Basket!$J$2:$J$43) -> 1
A33: 10 | B33: Yogurt single cup vs large tub | C33: =COUNTIF(Basket!$A$2:$A$43,A33) -> 2 | D33: =SUMIF(Basket!$A$2:$A$43,A33,Basket!$J$2:$J$43) -> 1
A34: 11 | B34: Method foaming soap pump vs refill | C34: =COUNTIF(Basket!$A$2:$A$43,A34) -> 2 | D34: =SUMIF(Basket!$A$2:$A$43,A34,Basket!$J$2:$J$43) -> 1
A35: 12 | B35: Aveeno body wash pump vs refill | C35: =COUNTIF(Basket!$A$2:$A$43,A35) -> 2 | D35: =SUMIF(Basket!$A$2:$A$43,A35,Basket!$J$2:$J$43) -> 1
... A43: 20 | B43: Surface cleaner spray vs refill tablets | C43: =COUNTIF(Basket!$A$2:$A$43,A43) -> 2 | D43: =SUMIF(Basket!$A$2:$A$43,A43,Basket!$J$2:$J$43) -> 1
